pixelateme/__init__.py
pixelateme/_version.py
pixelateme/blur.py
pixelateme/centerface.onnx
pixelateme/centerface.py
pixelateme/cli.py
pixelateme/face_detection.py
pixelateme/gui.py
pixelateme/main.py
PixelateMe-1.1.0.dist-info/METADATA
PixelateMe-1.1.0.dist-info/WHEEL
PixelateMe-1.1.0.dist-info/entry_points.txt
PixelateMe-1.1.0.dist-info/top_level.txt
PixelateMe-1.1.0.dist-info/RECORD
