Metadata-Version: 2.1
Name: PixelateMe
Version: 1.1.0
Summary: A Python CLI-Tool and package to pixelate or blur faces in images and videos.
Home-page: https://github.com/mbpictures/pixelateme
Author: Marius Butz
Classifier: Programming Language :: Python :: 3
Classifier: License :: OSI Approved :: MIT License
Classifier: Operating System :: OS Independent
Requires-Python: >=3.6
Requires-Dist: deepface
Requires-Dist: tqdm
Requires-Dist: opencv-python
Requires-Dist: onnx
Requires-Dist: onnxruntime
Requires-Dist: gooey
Provides-Extra: gpu
Requires-Dist: onnxruntime-gpu ; extra == 'gpu'
